ppf/webref/__init__.py
ppf/webref/cli.py
ppf/webref/model.py
ppf/webref/secrets.py
ppf/webref/static/script.js
ppf/webref/static/style.css
ppf/webref/templates/entry_table.tmpl
ppf/webref/templates/index.php
ppf/webref/templates/login.php
ppf.webref-0.1.1.dist-info/LICENSE
ppf.webref-0.1.1.dist-info/METADATA
ppf.webref-0.1.1.dist-info/WHEEL
ppf.webref-0.1.1.dist-info/top_level.txt
ppf.webref-0.1.1.dist-info/RECORD
