Metadata-Version: 2.1
Name: ppf.webref
Version: 0.1.1
Summary: Flask app providing a web-interface to a JabRef database
Home-page: https://github.com/adrianschlatter/ppf.webref/tree/master
Author: Adrian Schlatter
License: MIT
Project-URL: Bug Reports, https://github.com/adrianschlatter/ppf.webref/issues
Project-URL: Source, https://github.com/adrianschlatter/ppf.webref
Keywords: jabref,references,web,server,app
Classifier: Development Status :: 3 - Alpha
Classifier: Intended Audience :: Developers
Classifier: Intended Audience :: Information Technology
Classifier: License :: OSI Approved :: MIT License
Classifier: Programming Language :: Python :: 3
Classifier: Operating System :: OS Independent
Requires-Python: <4,>=3.6
License-File: LICENSE
Requires-Dist: flask
Requires-Dist: flask-sqlalchemy
Requires-Dist: flask-talisman
Requires-Dist: flask-login
Requires-Dist: flask-wtf
Requires-Dist: flask-bcrypt
Requires-Dist: pymysql
Requires-Dist: ppf.jabref
Requires-Dist: plumbum
Requires-Dist: importlib-metadata ; python_version < "3.8"
Provides-Extra: dev
Requires-Dist: build ; extra == 'dev'
Requires-Dist: tox ; extra == 'dev'
Requires-Dist: twine ; extra == 'dev'
Provides-Extra: test
Requires-Dist: check-manifest ; extra == 'test'
Requires-Dist: setuptools >=40.5.0 ; extra == 'test'
Requires-Dist: flake8 ; extra == 'test'
Requires-Dist: pytest ; extra == 'test'
Requires-Dist: pytest-cov ; extra == 'test'
Requires-Dist: coverage ; extra == 'test'
